strands_tools/__init__.py
strands_tools/a2a_client.py
strands_tools/agent_core_memory.py
strands_tools/agent_graph.py
strands_tools/batch.py
strands_tools/bright_data.py
strands_tools/calculator.py
strands_tools/chat_video.py
strands_tools/cron.py
strands_tools/current_time.py
strands_tools/diagram.py
strands_tools/editor.py
strands_tools/elasticsearch_memory.py
strands_tools/environment.py
strands_tools/exa.py
strands_tools/file_read.py
strands_tools/file_write.py
strands_tools/generate_image.py
strands_tools/generate_image_stability.py
strands_tools/graph.py
strands_tools/handoff_to_user.py
strands_tools/http_request.py
strands_tools/image_reader.py
strands_tools/journal.py
strands_tools/load_tool.py
strands_tools/mcp_client.py
strands_tools/mem0_memory.py
strands_tools/memory.py
strands_tools/mongodb_memory.py
strands_tools/nova_reels.py
strands_tools/python_repl.py
strands_tools/retrieve.py
strands_tools/rss.py
strands_tools/search_video.py
strands_tools/shell.py
strands_tools/slack.py
strands_tools/sleep.py
strands_tools/speak.py
strands_tools/stop.py
strands_tools/swarm.py
strands_tools/tavily.py
strands_tools/think.py
strands_tools/use_agent.py
strands_tools/use_aws.py
strands_tools/use_computer.py
strands_tools/use_llm.py
strands_tools/workflow.py
strands_tools/browser/__init__.py
strands_tools/browser/agent_core_browser.py
strands_tools/browser/browser.py
strands_tools/browser/local_chromium_browser.py
strands_tools/browser/models.py
strands_tools/code_interpreter/__init__.py
strands_tools/code_interpreter/agent_core_code_interpreter.py
strands_tools/code_interpreter/code_interpreter.py
strands_tools/code_interpreter/models.py
strands_tools/utils/__init__.py
strands_tools/utils/aws_util.py
strands_tools/utils/console_util.py
strands_tools/utils/data_util.py
strands_tools/utils/detect_language.py
strands_tools/utils/generate_schema_util.py
strands_tools/utils/user_input.py
strands_tools/utils/models/__init__.py
strands_tools/utils/models/anthropic.py
strands_agents_tools-0.2.18.dist-info/METADATA
strands_agents_tools-0.2.18.dist-info/WHEEL
strands_agents_tools-0.2.18.dist-info/licenses/LICENSE
strands_agents_tools-0.2.18.dist-info/licenses/NOTICE
strands_agents_tools-0.2.18.dist-info/RECORD
