Metadata-Version: 2.4
Name: strands-agents-tools
Version: 0.2.18
Summary: A collection of specialized tools for Strands Agents
Project-URL: Homepage, https://github.com/strands-agents/tools
Project-URL: Bug Tracker, https://github.com/strands-agents/tools/issues
Project-URL: Documentation, https://strandsagents.com/
Author-email: AWS <opensource@amazon.com>
License: Apache-2.0
License-File: LICENSE
License-File: NOTICE
Classifier: Development Status :: 4 - Beta
Classifier: Intended Audience :: Developers
Classifier: License :: OSI Approved :: Apache Software License
Classifier: Operating System :: OS Independent
Classifier: Programming Language :: Python :: 3
Classifier: Programming Language :: Python :: 3.10
Classifier: Programming Language :: Python :: 3.11
Classifier: Programming Language :: Python :: 3.12
Classifier: Programming Language :: Python :: 3.13
Classifier: Programming Language :: Python :: 3.14
Classifier: Topic :: Scientific/Engineering :: Artificial Intelligence
Classifier: Topic :: Software Development :: Libraries :: Python Modules
Requires-Python: >=3.10
Requires-Dist: aiohttp<4.0.0,>=3.8.0
Requires-Dist: aws-requests-auth<0.5.0,>=0.4.3
Requires-Dist: botocore<2.0.0,>=1.39.7
Requires-Dist: dill<0.5.0,>=0.4.0
Requires-Dist: markdownify<2.0.0,>=1.0.0
Requires-Dist: pillow<12.0.0,>=11.2.1
Requires-Dist: prompt-toolkit<4.0.0,>=3.0.51
Requires-Dist: pyjwt<3.0.0,>=2.10.1
Requires-Dist: requests<3.0.0,>=2.28.0
Requires-Dist: rich<15.0.0,>=14.0.0
Requires-Dist: slack-bolt<2.0.0,>=1.23.0
Requires-Dist: strands-agents>=1.0.0
Requires-Dist: sympy<2.0.0,>=1.12.0
Requires-Dist: tenacity<10.0.0,>=9.1.2
Requires-Dist: typing-extensions<5.0.0,>=4.0.0
Requires-Dist: tzdata; platform_system == 'Windows'
Requires-Dist: watchdog<7.0.0,>=6.0.0
Provides-Extra: a2a-client
Requires-Dist: a2a-sdk[sql]<0.4.0,>=0.3.0; extra == 'a2a-client'
Provides-Extra: agent-core-browser
Requires-Dist: bedrock-agentcore==0.1.0; extra == 'agent-core-browser'
Requires-Dist: nest-asyncio<2.0.0,>=1.5.0; extra == 'agent-core-browser'
Requires-Dist: playwright<2.0.0,>=1.42.0; extra == 'agent-core-browser'
Provides-Extra: agent-core-code-interpreter
Requires-Dist: bedrock-agentcore==0.1.0; extra == 'agent-core-code-interpreter'
Provides-Extra: build
Requires-Dist: hatch<1.16.0,>=1.0.0; extra == 'build'
Provides-Extra: dev
Requires-Dist: commitizen<5.0.0,>=4.4.0; extra == 'dev'
Requires-Dist: hatch<1.16.0,>=1.0.0; extra == 'dev'
Requires-Dist: mem0ai<1.0.0,>=0.1.104; extra == 'dev'
Requires-Dist: mypy<1.0.0,>=0.981; extra == 'dev'
Requires-Dist: nest-asyncio<2.0.0,>=1.5.0; extra == 'dev'
Requires-Dist: opensearch-py<3.0.0,>=2.8.0; extra == 'dev'
Requires-Dist: playwright<2.0.0,>=1.42.0; extra == 'dev'
Requires-Dist: pre-commit<4.2.0,>=3.2.0; extra == 'dev'
Requires-Dist: pytest<9.0.0,>=8.0.0; extra == 'dev'
Requires-Dist: responses<1.0.0,>=0.6.1; extra == 'dev'
Requires-Dist: ruff<0.14.0,>=0.13.0; extra == 'dev'
Requires-Dist: twelvelabs<1.0.0,>=0.4.0; extra == 'dev'
Provides-Extra: diagram
Requires-Dist: diagrams<1.0.0,>=0.23.0; extra == 'diagram'
Requires-Dist: graphviz<1.0.0,>=0.20.0; extra == 'diagram'
Requires-Dist: matplotlib<4.0.0,>=3.5.0; extra == 'diagram'
Requires-Dist: networkx<4.0.0,>=2.8.0; extra == 'diagram'
Provides-Extra: docs
Requires-Dist: sphinx-autodoc-typehints<2.0.0,>=1.12.0; extra == 'docs'
Requires-Dist: sphinx-rtd-theme<2.0.0,>=1.0.0; extra == 'docs'
Requires-Dist: sphinx<6.0.0,>=5.0.0; extra == 'docs'
Provides-Extra: elasticsearch-memory
Requires-Dist: elasticsearch<9.0.0,>=8.0.0; extra == 'elasticsearch-memory'
Provides-Extra: local-chromium-browser
Requires-Dist: nest-asyncio<2.0.0,>=1.5.0; extra == 'local-chromium-browser'
Requires-Dist: playwright<2.0.0,>=1.42.0; extra == 'local-chromium-browser'
Provides-Extra: mem0-memory
Requires-Dist: mem0ai<1.0.0,>=0.1.99; extra == 'mem0-memory'
Requires-Dist: opensearch-py<3.0.0,>=2.8.0; extra == 'mem0-memory'
Provides-Extra: mongodb-memory
Requires-Dist: pymongo<5.0.0,>=4.0.0; extra == 'mongodb-memory'
Provides-Extra: rss
Requires-Dist: feedparser<7.0.0,>=6.0.10; extra == 'rss'
Requires-Dist: html2text<2021.0.0,>=2020.1.16; extra == 'rss'
Provides-Extra: twelvelabs
Requires-Dist: twelvelabs<1.0.0,>=0.4.0; extra == 'twelvelabs'
Provides-Extra: use-computer
Requires-Dist: opencv-python<5.0.0,>=4.5.0; extra == 'use-computer'
Requires-Dist: psutil<6.0.0,>=5.8.0; extra == 'use-computer'
Requires-Dist: pyautogui<1.0.0,>=0.9.53; extra == 'use-computer'
Requires-Dist: pytesseract<1.0.0,>=0.3.8; extra == 'use-computer'
